meraki_dashboard/__init__.py
meraki_dashboard/meraki_dashboard.py
meraki_dashboard-0.1.1.dist-info/LICENSE
meraki_dashboard-0.1.1.dist-info/METADATA
meraki_dashboard-0.1.1.dist-info/WHEEL
meraki_dashboard-0.1.1.dist-info/top_level.txt
meraki_dashboard-0.1.1.dist-info/RECORD
