Metadata-Version: 2.2
Name: meraki_dashboard
Version: 0.1.1
Summary: Python library for scraping your meraki dashboard of the data necessary to automate functions not available in the public API.
Author-email: Lawrence Lucas <llucas@starbucks.com>
Project-URL: Homepage, https://github.com/llucas-sb/meraki_dashboard
Project-URL: Issues, https://github.com/llucas-sb/meraki_dashboard/issues
Classifier: Programming Language :: Python :: 3
Classifier: Operating System :: OS Independent
Classifier: License :: OSI Approved :: MIT License
Requires-Python: >=3.8
License-File: LICENSE
Requires-Dist: requests==2.32.3
